django_notify_framework/__init__.py
django_notify_framework/apps.py
django_notify_framework/conf.py
django_notify_framework/notify/__init__.py
django_notify_framework/notify/urls.py
django_notify_framework/notify/views.py
django_notify_framework/templates/notify/home.html
django_notify_framework-0.0.11.dist-info/licenses/LICENSE
django_notify_framework-0.0.11.dist-info/METADATA
django_notify_framework-0.0.11.dist-info/WHEEL
django_notify_framework-0.0.11.dist-info/top_level.txt
django_notify_framework-0.0.11.dist-info/RECORD
