Metadata-Version: 2.4
Name: django-notify-framework
Version: 0.0.11
Summary: Easy-to-integrate Django notification library with WebSocket support for real-time updates. (under development)
Home-page: https://github.com/RahulSaini3125/django_notify_framework
Author: Rahul Saini
Author-email: rahulsaini5123@outlook.com
License: MIT
Classifier: Framework :: Django
Classifier: Programming Language :: Python :: 3
Classifier: Operating System :: OS Independent
Requires-Python: >=3.6
License-File: LICENSE
Requires-Dist: Django>=3.2
Dynamic: author
Dynamic: author-email
Dynamic: classifier
Dynamic: description
Dynamic: description-content-type
Dynamic: home-page
Dynamic: license
Dynamic: license-file
Dynamic: requires-dist
Dynamic: requires-python
Dynamic: summary
